LICENSE
MANIFEST.in
README.rst
nova_limits.py
setup.py
test_nova_limits.py
bin/limit_class
nova_limits.egg-info/PKG-INFO
nova_limits.egg-info/SOURCES.txt
nova_limits.egg-info/dependency_links.txt
nova_limits.egg-info/entry_points.txt
nova_limits.egg-info/requires.txt
nova_limits.egg-info/top_level.txt