Metadata-Version: 1.0
Name: nova-limits
Version: 0.5.1
Summary: Nova-specific rate-limit class for turnstile
Home-page: https://github.com/klmitch/nova_limits
Author: Kevin L. Mitchell
Author-email: kevin.mitchell@rackspace.com
License: Apache License (2.0)
Platform: UNKNOWN
Classifier: Development Status :: 4 - Beta
Classifier: Environment :: Web Environment
Classifier: Framework :: Paste
Classifier: Intended Audience :: System Administrators
Classifier: License :: OSI Approved :: Apache Software License
Classifier: Programming Language :: Python
Classifier: Topic :: Internet :: WWW/HTTP :: WSGI :: Middleware
